vizwiz.py
vizwiz_fewshot-1.0.2.dist-info/LICENSE
vizwiz_fewshot-1.0.2.dist-info/METADATA
vizwiz_fewshot-1.0.2.dist-info/WHEEL
vizwiz_fewshot-1.0.2.dist-info/top_level.txt
vizwiz_fewshot-1.0.2.dist-info/RECORD
