Metadata-Version: 2.1
Name: vizwiz-fewshot
Version: 1.0.2
Summary: VizWiz-FewShot dataset API
Author-email: Alec Bell <alexander.bell-1@colorado.edu>
License: MIT License        
Project-URL: Homepage, https://github.com/alec-bell/vizwiz-fewshot
Keywords: feed,reader,tutorial
Classifier: License :: OSI Approved :: MIT License
Classifier: Programming Language :: Python
Classifier: Programming Language :: Python :: 3
Requires-Python: >=3.9
License-File: LICENSE
Requires-Dist: pillow
Requires-Dist: torch
